MANIFEST.in
README.rst
setup.cfg
setup.py
alignak_app/__init__.py
alignak_app/alignakapp.py
alignak_app/app.py
alignak_app.egg-info/PKG-INFO
alignak_app.egg-info/SOURCES.txt
alignak_app.egg-info/dependency_links.txt
alignak_app.egg-info/entry_points.txt
alignak_app.egg-info/not-zip-safe
alignak_app.egg-info/requires.txt
alignak_app.egg-info/top_level.txt
alignak_app/backend/__init__.py
alignak_app/backend/backend.py
alignak_app/backend/datamanager.py
alignak_app/backend/ws_client.py
alignak_app/items/__init__.py
alignak_app/items/daemon.py
alignak_app/items/event.py
alignak_app/items/history.py
alignak_app/items/host.py
alignak_app/items/item.py
alignak_app/items/livesynthesis.py
alignak_app/items/period.py
alignak_app/items/realm.py
alignak_app/items/service.py
alignak_app/items/user.py
alignak_app/locales/POTFILES.ini
alignak_app/locales/__init__.py
alignak_app/locales/locales.py
alignak_app/locales/messages.pot
alignak_app/locales/LC_MESSAGES/en_US.mo
alignak_app/locales/LC_MESSAGES/en_US.po
alignak_app/locales/LC_MESSAGES/fr_FR.mo
alignak_app/locales/LC_MESSAGES/fr_FR.po
alignak_app/qobjects/__init__.py
alignak_app/qobjects/about.py
alignak_app/qobjects/app_main.py
alignak_app/qobjects/dock.py
alignak_app/qobjects/panel.py
alignak_app/qobjects/alignak/__init__.py
alignak_app/qobjects/alignak/alignak.py
alignak_app/qobjects/alignak/dashboard.py
alignak_app/qobjects/alignak/livestate.py
alignak_app/qobjects/alignak/problems.py
alignak_app/qobjects/alignak/problems_table.py
alignak_app/qobjects/alignak/status.py
alignak_app/qobjects/common/__init__.py
alignak_app/qobjects/common/actions.py
alignak_app/qobjects/common/buttons.py
alignak_app/qobjects/common/dialogs.py
alignak_app/qobjects/common/frames.py
alignak_app/qobjects/common/labels.py
alignak_app/qobjects/common/widgets.py
alignak_app/qobjects/events/__init__.py
alignak_app/qobjects/events/events.py
alignak_app/qobjects/events/item.py
alignak_app/qobjects/events/spy.py
alignak_app/qobjects/events/spy_list.py
alignak_app/qobjects/host/__init__.py
alignak_app/qobjects/host/customs.py
alignak_app/qobjects/host/history.py
alignak_app/qobjects/host/host.py
alignak_app/qobjects/host/synthesis.py
alignak_app/qobjects/login/__init__.py
