Metadata-Version: 1.1
Name: alignak-app
Version: 1.4.4
Summary: Desktop application, with system tray, for Alignak monitoring solution
Home-page: https://github.com/Alignak-monitoring-contrib/alignak-app
Author: Estrada Matthieu
Author-email: ttamalfor@gmail.com
License: GNU Affero General Public License, version 3
Keywords: alignak application monitoring
Platform: UNKNOWN
Classifier: Development Status :: 5 - Production/Stable
Classifier: Environment :: X11 Applications :: Qt
Classifier: Intended Audience :: End Users/Desktop
Classifier: Intended Audience :: Developers
Classifier: Intended Audience :: Customer Service
Classifier: Intended Audience :: System Administrators
Classifier: License :: OSI Approved :: GNU General Public License v3 (GPLv3)
Classifier: Natural Language :: English
Classifier: Programming Language :: Python :: 3
Classifier: Topic :: System :: Monitoring
Classifier: Topic :: System :: Systems Administration
Classifier: Topic :: Desktop Environment
